polysign/__init__.py
polysign/signer.py
polysign/signer_btc.py
polysign/signer_crw.py
polysign/signer_ecdsa.py
polysign/signer_ed25519.py
polysign/signer_rsa.py
polysign/signerfactory.py
Polysign-0.1.4.dist-info/AUTHORS.rst
Polysign-0.1.4.dist-info/LICENSE
Polysign-0.1.4.dist-info/METADATA
Polysign-0.1.4.dist-info/WHEEL
Polysign-0.1.4.dist-info/top_level.txt
Polysign-0.1.4.dist-info/RECORD
