Metadata-Version: 2.1
Name: Polysign
Version: 0.1.4
Summary: Polysign PIP module for Bismuth. Handles the various cryptographic primitives Bismuth Crypto currency supports.
Home-page: https://github.com/bismuthfoundation/polysign
Author: EggdraSyl from Bismuth Foundation
Author-email: dev@eggpool.net
License: MIT license
Keywords: polysign
Platform: UNKNOWN
Classifier: Development Status :: 5 - Production/Stable
Classifier: Intended Audience :: Developers
Classifier: License :: OSI Approved :: MIT License
Classifier: Natural Language :: English
Classifier: Programming Language :: Python :: 3.6
Classifier: Programming Language :: Python :: 3.7
Requires-Dist: pycryptodomex
Requires-Dist: ed25519
Requires-Dist: pynacl
Requires-Dist: base58
Requires-Dist: coincurve
